README.txt
bootstrap.py
buildout.cfg
setup.cfg
setup.py
docs/HISTORY.txt
docs/INSTALL.txt
docs/LICENSE.txt
ely/__init__.py
ely.advancedquery.egg-info/PKG-INFO
ely.advancedquery.egg-info/SOURCES.txt
ely.advancedquery.egg-info/dependency_links.txt
ely.advancedquery.egg-info/entry_points.txt
ely.advancedquery.egg-info/namespace_packages.txt
ely.advancedquery.egg-info/not-zip-safe
ely.advancedquery.egg-info/requires.txt
ely.advancedquery.egg-info/top_level.txt
ely/advancedquery/README.txt
ely/advancedquery/__init__.py
ely/advancedquery/configure.zcml
ely/advancedquery/interfaces.py
ely/advancedquery/utility.py
ely/advancedquery/version.txt
ely/advancedquery/tests/__init__.py
ely/advancedquery/tests/tests.py