Metadata-Version: 1.0
Name: ely.advancedquery
Version: 1.1
Summary: Advanced Query wraps the Advanced Query extension to zope's ZCatalog (http://www.dieter.handshake.de/pyprojects/zope/AdvancedQuery.html) for use in plone.
Home-page: http://ely.googlecode.com/svn/ely.advancedquery/trunk
Author: Matt Halstead
Author-email: matt@elyt.com
License: new BSD
Keywords: zope plone catalog query
Platform: UNKNOWN
Classifier: Framework :: Plone
Classifier: Framework :: Zope2
Classifier: Framework :: Zope3
Classifier: Programming Language :: Python
Classifier: Topic :: Software Development :: Libraries :: Python Modules
